{
  "generated_at": "2026-07-16T02:49:47.356905",
  "status": "ok_fallback",
  "message": "Model V2 accuracy audit generated, but at least one mode used fallback inference",
  "input": {
    "feature_rows": 51841,
    "candidate_count": 11612,
    "audited_trade_count": 11560,
    "v2_recommended_count": 5959,
    "active_modes": [
      "t1",
      "swing"
    ],
    "max_candidates_per_day": 5,
    "precision_top_k": [
      3,
      5
    ],
    "probability_threshold_grid": [
      0.45,
      0.5,
      0.52,
      0.55,
      0.6,
      0.65,
      0.7,
      0.75
    ]
  },
  "report_paths": {
    "json": "reports/model_v2_accuracy_audit.json",
    "by_ticker_csv": "reports/model_v2_by_ticker.csv",
    "by_regime_csv": "reports/model_v2_by_regime.csv",
    "threshold_candidates_csv": "reports/model_v2_threshold_candidates.csv"
  },
  "infer": {
    "status": "ok",
    "message": "Shadow inference completed",
    "modes": {
      "swing": {
        "rows": 5637,
        "source": "fallback",
        "threshold": 0.55,
        "thresholds_by_regime": {},
        "metadata": {}
      },
      "t1": {
        "rows": 5975,
        "source": "fallback",
        "threshold": 0.52,
        "thresholds_by_regime": {},
        "metadata": {}
      }
    },
    "rows": 11612
  },
  "model_source": {
    "candidate_sources": {
      "fallback": 11560
    },
    "mode_sources": {
      "swing": {
        "source": "fallback",
        "rows": 5637,
        "threshold": 0.55
      },
      "t1": {
        "source": "fallback",
        "rows": 5975,
        "threshold": 0.52
      }
    },
    "has_fallback": true
  },
  "overall_candidates": {
    "trade_count": 11560,
    "precision_pct": 33.75,
    "expectancy_r": -0.1279,
    "profit_factor_r": 0.6209,
    "avg_win_r": 0.6209,
    "avg_loss_r": -0.5094,
    "avg_mae_r": -0.509,
    "worst_mae_r": -3.773,
    "avg_mfe_r": 0.546,
    "median_score": 81.416,
    "tp1_touch_rate_pct": 17.36,
    "tp2_hit_rate_pct": 4.9,
    "stop_rate_pct": 18.09,
    "breakeven_rate_pct": 4.96
  },
  "v2_recommended": {
    "trade_count": 5959,
    "precision_pct": 33.63,
    "expectancy_r": -0.1005,
    "profit_factor_r": 0.5333,
    "avg_win_r": 0.3414,
    "avg_loss_r": -0.3244,
    "avg_mae_r": -0.2997,
    "worst_mae_r": -2.4107,
    "avg_mfe_r": 0.3111,
    "median_score": 96.773,
    "tp1_touch_rate_pct": 5.07,
    "tp2_hit_rate_pct": 0.99,
    "stop_rate_pct": 2.92,
    "breakeven_rate_pct": 0.59
  },
  "selection_comparison": {
    "v1_baseline": {
      "trade_count": 5090,
      "precision_pct": 33.14,
      "expectancy_r": -0.1002,
      "profit_factor_r": 0.6241,
      "avg_win_r": 0.5018,
      "avg_loss_r": -0.3986,
      "avg_mae_r": -0.3864,
      "worst_mae_r": -2.5002,
      "avg_mfe_r": 0.4285,
      "median_score": 97.5509,
      "tp1_touch_rate_pct": 11.1,
      "tp2_hit_rate_pct": 3.5,
      "stop_rate_pct": 9.57,
      "breakeven_rate_pct": 2.93
    },
    "v2_recommended": {
      "trade_count": 5959,
      "precision_pct": 33.63,
      "expectancy_r": -0.1005,
      "profit_factor_r": 0.5333,
      "avg_win_r": 0.3414,
      "avg_loss_r": -0.3244,
      "avg_mae_r": -0.2997,
      "worst_mae_r": -2.4107,
      "avg_mfe_r": 0.3111,
      "median_score": 96.773,
      "tp1_touch_rate_pct": 5.07,
      "tp2_hit_rate_pct": 0.99,
      "stop_rate_pct": 2.92,
      "breakeven_rate_pct": 0.59
    },
    "overlap": {
      "trade_count": 4247,
      "precision_pct": 33.69,
      "expectancy_r": -0.0924,
      "profit_factor_r": 0.5764,
      "avg_win_r": 0.3733,
      "avg_loss_r": -0.3291,
      "avg_mae_r": -0.3086,
      "worst_mae_r": -2.4025,
      "avg_mfe_r": 0.3323,
      "median_score": 98.3265,
      "tp1_touch_rate_pct": 6.24,
      "tp2_hit_rate_pct": 1.34,
      "stop_rate_pct": 3.3,
      "breakeven_rate_pct": 0.82
    },
    "v1_only": {
      "trade_count": 843,
      "precision_pct": 30.37,
      "expectancy_r": -0.1391,
      "profit_factor_r": 0.727,
      "avg_win_r": 1.2198,
      "avg_loss_r": -0.7318,
      "avg_mae_r": -0.7779,
      "worst_mae_r": -2.5002,
      "avg_mfe_r": 0.9129,
      "median_score": 72.19,
      "tp1_touch_rate_pct": 35.59,
      "tp2_hit_rate_pct": 14.35,
      "stop_rate_pct": 41.16,
      "breakeven_rate_pct": 13.52
    },
    "v2_only": {
      "trade_count": 1712,
      "precision_pct": 33.47,
      "expectancy_r": -0.1205,
      "profit_factor_r": 0.4209,
      "avg_win_r": 0.2617,
      "avg_loss_r": -0.3127,
      "avg_mae_r": -0.2775,
      "worst_mae_r": -2.4107,
      "avg_mfe_r": 0.2583,
      "median_score": 93.2534,
      "tp1_touch_rate_pct": 2.16,
      "tp2_hit_rate_pct": 0.12,
      "stop_rate_pct": 1.99,
      "breakeven_rate_pct": 0.0
    },
    "overlap_count": 4247,
    "v1_count": 5090,
    "v2_count": 5959
  },
  "by_mode": {
    "swing": {
      "trade_count": 5590,
      "precision_pct": 33.79,
      "expectancy_r": -0.156,
      "profit_factor_r": 0.6735,
      "avg_win_r": 0.9522,
      "avg_loss_r": -0.7216,
      "avg_mae_r": -0.7485,
      "worst_mae_r": -3.773,
      "avg_mfe_r": 0.8216,
      "median_score": 56.95,
      "tp1_touch_rate_pct": 31.81,
      "tp2_hit_rate_pct": 9.8,
      "stop_rate_pct": 35.65,
      "breakeven_rate_pct": 10.25
    },
    "t1": {
      "trade_count": 5970,
      "precision_pct": 33.7,
      "expectancy_r": -0.1017,
      "profit_factor_r": 0.5067,
      "avg_win_r": 0.3099,
      "avg_loss_r": -0.3109,
      "avg_mae_r": -0.2848,
      "worst_mae_r": -3.4339,
      "avg_mfe_r": 0.288,
      "median_score": 96.769,
      "tp1_touch_rate_pct": 3.84,
      "tp2_hit_rate_pct": 0.32,
      "stop_rate_pct": 1.64,
      "breakeven_rate_pct": 0.0
    }
  },
  "v2_by_mode": {
    "swing": {
      "trade_count": 186,
      "precision_pct": 28.49,
      "expectancy_r": -0.0906,
      "profit_factor_r": 0.8291,
      "avg_win_r": 1.5417,
      "avg_loss_r": -0.7411,
      "avg_mae_r": -0.8065,
      "worst_mae_r": -2.0073,
      "avg_mfe_r": 1.0,
      "median_score": 80.985,
      "tp1_touch_rate_pct": 43.01,
      "tp2_hit_rate_pct": 21.51,
      "stop_rate_pct": 43.55,
      "breakeven_rate_pct": 18.82
    },
    "t1": {
      "trade_count": 5773,
      "precision_pct": 33.8,
      "expectancy_r": -0.1008,
      "profit_factor_r": 0.5087,
      "avg_win_r": 0.3088,
      "avg_loss_r": -0.3099,
      "avg_mae_r": -0.2834,
      "worst_mae_r": -2.4107,
      "avg_mfe_r": 0.2889,
      "median_score": 96.93,
      "tp1_touch_rate_pct": 3.85,
      "tp2_hit_rate_pct": 0.33,
      "stop_rate_pct": 1.61,
      "breakeven_rate_pct": 0.0
    }
  },
  "precision_at_k": {
    "combined": [
      {
        "k": 3,
        "sample_count": 6998,
        "precision_pct": 33.44,
        "expectancy_r": -0.1273,
        "profit_factor_r": 0.6332
      },
      {
        "k": 5,
        "sample_count": 11560,
        "precision_pct": 33.75,
        "expectancy_r": -0.1279,
        "profit_factor_r": 0.6209
      }
    ],
    "by_mode": {
      "swing": [
        {
          "k": 3,
          "sample_count": 3416,
          "precision_pct": 33.67,
          "expectancy_r": -0.1469,
          "profit_factor_r": 0.6964
        },
        {
          "k": 5,
          "sample_count": 5590,
          "precision_pct": 33.79,
          "expectancy_r": -0.156,
          "profit_factor_r": 0.6735
        }
      ],
      "t1": [
        {
          "k": 3,
          "sample_count": 3582,
          "precision_pct": 33.22,
          "expectancy_r": -0.1086,
          "profit_factor_r": 0.4984
        },
        {
          "k": 5,
          "sample_count": 5970,
          "precision_pct": 33.7,
          "expectancy_r": -0.1017,
          "profit_factor_r": 0.5067
        }
      ]
    }
  },
  "calibration_all_candidates": {
    "status": "ok",
    "source": "shadow_p_win",
    "ece": 0.246851,
    "ece_pct": 24.69,
    "bins": [
      {
        "bin": "(-0.001, 0.2]",
        "sample_count": 312,
        "avg_predicted_p_win_pct": 13.75,
        "actual_win_rate_pct": 31.41,
        "abs_error_pct": 17.66
      },
      {
        "bin": "(0.2, 0.4]",
        "sample_count": 3219,
        "avg_predicted_p_win_pct": 32.28,
        "actual_win_rate_pct": 35.2,
        "abs_error_pct": 2.92
      },
      {
        "bin": "(0.4, 0.6]",
        "sample_count": 2298,
        "avg_predicted_p_win_pct": 46.76,
        "actual_win_rate_pct": 31.98,
        "abs_error_pct": 14.78
      },
      {
        "bin": "(0.6, 0.8]",
        "sample_count": 4987,
        "avg_predicted_p_win_pct": 73.96,
        "actual_win_rate_pct": 33.89,
        "abs_error_pct": 40.07
      },
      {
        "bin": "(0.8, 1.0]",
        "sample_count": 744,
        "avg_predicted_p_win_pct": 82.17,
        "actual_win_rate_pct": 32.93,
        "abs_error_pct": 49.24
      }
    ]
  },
  "calibration_v2_recommended": {
    "status": "ok",
    "source": "shadow_p_win",
    "ece": 0.407284,
    "ece_pct": 40.73,
    "bins": [
      {
        "bin": "(0.4, 0.6]",
        "sample_count": 228,
        "avg_predicted_p_win_pct": 57.5,
        "actual_win_rate_pct": 30.26,
        "abs_error_pct": 27.24
      },
      {
        "bin": "(0.6, 0.8]",
        "sample_count": 4987,
        "avg_predicted_p_win_pct": 73.96,
        "actual_win_rate_pct": 33.89,
        "abs_error_pct": 40.07
      },
      {
        "bin": "(0.8, 1.0]",
        "sample_count": 744,
        "avg_predicted_p_win_pct": 82.17,
        "actual_win_rate_pct": 32.93,
        "abs_error_pct": 49.24
      }
    ]
  },
  "signal_decay_v2_recommended": [
    {
      "day": 1,
      "sample_count": 5959,
      "avg_decay_r": -0.0992,
      "positive_rate_pct": 33.95
    },
    {
      "day": 2,
      "sample_count": 5954,
      "avg_decay_r": -0.1003,
      "positive_rate_pct": 37.4
    },
    {
      "day": 3,
      "sample_count": 5949,
      "avg_decay_r": -0.0958,
      "positive_rate_pct": 39.5
    }
  ],
  "best_thresholds": {
    "swing": {
      "mode": "swing",
      "threshold": 0.65,
      "trade_count": 12,
      "selection_rate_pct": 0.21,
      "precision_pct": 41.67,
      "expectancy_r": 0.2489,
      "profit_factor_r": 1.4773,
      "avg_win_r": 1.8492,
      "avg_loss_r": -0.8941,
      "avg_mae_r": -0.7272,
      "avg_mfe_r": 1.2605
    },
    "t1": {
      "mode": "t1",
      "threshold": 0.65,
      "trade_count": 5647,
      "selection_rate_pct": 94.59,
      "precision_pct": 33.79,
      "expectancy_r": -0.1001,
      "profit_factor_r": 0.5121,
      "avg_win_r": 0.311,
      "avg_loss_r": -0.3099,
      "avg_mae_r": -0.2831,
      "avg_mfe_r": 0.2897
    }
  },
  "false_positive_summary": {
    "negative_signal_count": 3955,
    "negative_signal_rate_pct": 66.37,
    "weak_groups": {
      "ticker": [
        {
          "ticker": "ICBP",
          "trade_count": 93,
          "precision_pct": 24.73,
          "expectancy_r": -0.2499,
          "profit_factor_r": 0.1514,
          "avg_win_r": 0.1803,
          "avg_loss_r": -0.3913,
          "avg_mae_r": -0.3794,
          "worst_mae_r": -1.726,
          "avg_mfe_r": 0.154,
          "median_score": 94.4822,
          "tp1_touch_rate_pct": 1.08,
          "tp2_hit_rate_pct": 0.0,
          "stop_rate_pct": 5.38,
          "breakeven_rate_pct": 0.0,
          "live_trade_count": 44,
          "live_expectancy_r": -0.2627,
          "live_profit_factor_r": 0.1332
        },
        {
          "ticker": "BBCA",
          "trade_count": 38,
          "precision_pct": 23.68,
          "expectancy_r": -0.2241,
          "profit_factor_r": 0.178,
          "avg_win_r": 0.2049,
          "avg_loss_r": -0.3573,
          "avg_mae_r": -0.3046,
          "worst_mae_r": -1.1744,
          "avg_mfe_r": 0.2066,
          "median_score": 94.7405,
          "tp1_touch_rate_pct": 2.63,
          "tp2_hit_rate_pct": 0.0,
          "stop_rate_pct": 2.63,
          "breakeven_rate_pct": 0.0,
          "live_trade_count": 16,
          "live_expectancy_r": -0.1515,
          "live_profit_factor_r": 0.2943
        },
        {
          "ticker": "INDF",
          "trade_count": 75,
          "precision_pct": 30.67,
          "expectancy_r": -0.2143,
          "profit_factor_r": 0.1817,
          "avg_win_r": 0.1551,
          "avg_loss_r": -0.3776,
          "avg_mae_r": -0.3594,
          "worst_mae_r": -2.4107,
          "avg_mfe_r": 0.166,
          "median_score": 94.7651,
          "tp1_touch_rate_pct": 0.0,
          "tp2_hit_rate_pct": 0.0,
          "stop_rate_pct": 4.0,
          "breakeven_rate_pct": 0.0,
          "live_trade_count": 31,
          "live_expectancy_r": -0.2256,
          "live_profit_factor_r": 0.1357
        },
        {
          "ticker": "BBRI",
          "trade_count": 98,
          "precision_pct": 26.53,
          "expectancy_r": -0.2071,
          "profit_factor_r": 0.2219,
          "avg_win_r": 0.2225,
          "avg_loss_r": -0.3622,
          "avg_mae_r": -0.3057,
          "worst_mae_r": -1.8528,
          "avg_mfe_r": 0.2296,
          "median_score": 95.7088,
          "tp1_touch_rate_pct": 0.0,
          "tp2_hit_rate_pct": 0.0,
          "stop_rate_pct": 3.06,
          "breakeven_rate_pct": 0.0,
          "live_trade_count": 57,
          "live_expectancy_r": -0.1773,
          "live_profit_factor_r": 0.2364
        },
        {
          "ticker": "ASII",
          "trade_count": 87,
          "precision_pct": 24.14,
          "expectancy_r": -0.1933,
          "profit_factor_r": 0.2198,
          "avg_win_r": 0.2256,
          "avg_loss_r": -0.3266,
          "avg_mae_r": -0.3391,
          "worst_mae_r": -1.225,
          "avg_mfe_r": 0.1824,
          "median_score": 96.004,
          "tp1_touch_rate_pct": 1.15,
          "tp2_hit_rate_pct": 0.0,
          "stop_rate_pct": 2.3,
          "breakeven_rate_pct": 0.0,
          "live_trade_count": 51,
          "live_expectancy_r": -0.1591,
          "live_profit_factor_r": 0.2959
        },
        {
          "ticker": "AKRA",
          "trade_count": 200,
          "precision_pct": 28.0,
          "expectancy_r": -0.1905,
          "profit_factor_r": 0.2323,
          "avg_win_r": 0.206,
          "avg_loss_r": -0.3448,
          "avg_mae_r": -0.3121,
          "worst_mae_r": -1.3823,
          "avg_mfe_r": 0.2329,
          "median_score": 96.2622,
          "tp1_touch_rate_pct": 1.5,
          "tp2_hit_rate_pct": 0.0,
          "stop_rate_pct": 3.0,
          "breakeven_rate_pct": 0.0,
          "live_trade_count": 133,
          "live_expectancy_r": -0.1849,
          "live_profit_factor_r": 0.2596
        },
        {
          "ticker": "TLKM",
          "trade_count": 130,
          "precision_pct": 29.23,
          "expectancy_r": -0.184,
          "profit_factor_r": 0.2882,
          "avg_win_r": 0.2549,
          "avg_loss_r": -0.3653,
          "avg_mae_r": -0.3195,
          "worst_mae_r": -2.3423,
          "avg_mfe_r": 0.2186,
          "median_score": 95.0709,
          "tp1_touch_rate_pct": 1.54,
          "tp2_hit_rate_pct": 0.77,
          "stop_rate_pct": 3.08,
          "breakeven_rate_pct": 0.0,
          "live_trade_count": 73,
          "live_expectancy_r": -0.2238,
          "live_profit_factor_r": 0.2091
        },
        {
          "ticker": "KLBF",
          "trade_count": 120,
          "precision_pct": 28.33,
          "expectancy_r": -0.1797,
          "profit_factor_r": 0.2624,
          "avg_win_r": 0.2255,
          "avg_loss_r": -0.3398,
          "avg_mae_r": -0.3336,
          "worst_mae_r": -1.1107,
          "avg_mfe_r": 0.2299,
          "median_score": 96.4262,
          "tp1_touch_rate_pct": 0.83,
          "tp2_hit_rate_pct": 0.0,
          "stop_rate_pct": 1.67,
          "breakeven_rate_pct": 0.0,
          "live_trade_count": 73,
          "live_expectancy_r": -0.1806,
          "live_profit_factor_r": 0.2805
        },
        {
          "ticker": "MIKA",
          "trade_count": 148,
          "precision_pct": 27.03,
          "expectancy_r": -0.1706,
          "profit_factor_r": 0.267,
          "avg_win_r": 0.2299,
          "avg_loss_r": -0.3189,
          "avg_mae_r": -0.3276,
          "worst_mae_r": -1.0647,
          "avg_mfe_r": 0.2443,
          "median_score": 96.0601,
          "tp1_touch_rate_pct": 0.68,
          "tp2_hit_rate_pct": 0.0,
          "stop_rate_pct": 0.68,
          "breakeven_rate_pct": 0.0,
          "live_trade_count": 96,
          "live_expectancy_r": -0.1704,
          "live_profit_factor_r": 0.2641
        },
        {
          "ticker": "CPIN",
          "trade_count": 120,
          "precision_pct": 30.0,
          "expectancy_r": -0.1411,
          "profit_factor_r": 0.37,
          "avg_win_r": 0.2762,
          "avg_loss_r": -0.3199,
          "avg_mae_r": -0.3228,
          "worst_mae_r": -1.6899,
          "avg_mfe_r": 0.2473,
          "median_score": 95.7529,
          "tp1_touch_rate_pct": 1.67,
          "tp2_hit_rate_pct": 0.0,
          "stop_rate_pct": 3.33,
          "breakeven_rate_pct": 0.0,
          "live_trade_count": 72,
          "live_expectancy_r": -0.1298,
          "live_profit_factor_r": 0.432
        }
      ],
      "mode": [
        {
          "mode": "t1",
          "trade_count": 5773,
          "precision_pct": 33.8,
          "expectancy_r": -0.1008,
          "profit_factor_r": 0.5087,
          "avg_win_r": 0.3088,
          "avg_loss_r": -0.3099,
          "avg_mae_r": -0.2834,
          "worst_mae_r": -2.4107,
          "avg_mfe_r": 0.2889,
          "median_score": 96.93,
          "tp1_touch_rate_pct": 3.85,
          "tp2_hit_rate_pct": 0.33,
          "stop_rate_pct": 1.61,
          "breakeven_rate_pct": 0.0,
          "live_trade_count": 4062,
          "live_expectancy_r": -0.0928,
          "live_profit_factor_r": 0.5456
        },
        {
          "mode": "swing",
          "trade_count": 186,
          "precision_pct": 28.49,
          "expectancy_r": -0.0906,
          "profit_factor_r": 0.8291,
          "avg_win_r": 1.5417,
          "avg_loss_r": -0.7411,
          "avg_mae_r": -0.8065,
          "worst_mae_r": -2.0073,
          "avg_mfe_r": 1.0,
          "median_score": 80.985,
          "tp1_touch_rate_pct": 43.01,
          "tp2_hit_rate_pct": 21.51,
          "stop_rate_pct": 43.55,
          "breakeven_rate_pct": 18.82,
          "live_trade_count": 185,
          "live_expectancy_r": -0.0845,
          "live_profit_factor_r": 0.8394
        }
      ],
      "regime": [
        {
          "regime_status": "risk_off",
          "trade_count": 3808,
          "precision_pct": 33.27,
          "expectancy_r": -0.1048,
          "profit_factor_r": 0.5023,
          "avg_win_r": 0.318,
          "avg_loss_r": -0.3156,
          "avg_mae_r": -0.2957,
          "worst_mae_r": -2.4107,
          "avg_mfe_r": 0.2883,
          "median_score": 96.0198,
          "tp1_touch_rate_pct": 4.12,
          "tp2_hit_rate_pct": 0.71,
          "stop_rate_pct": 2.55,
          "breakeven_rate_pct": 0.32,
          "live_trade_count": 2409,
          "live_expectancy_r": -0.0898,
          "live_profit_factor_r": 0.5697
        },
        {
          "regime_status": "risk_on",
          "trade_count": 2151,
          "precision_pct": 34.26,
          "expectancy_r": -0.0928,
          "profit_factor_r": 0.5849,
          "avg_win_r": 0.3816,
          "avg_loss_r": -0.3401,
          "avg_mae_r": -0.3067,
          "worst_mae_r": -2.3423,
          "avg_mfe_r": 0.3514,
          "median_score": 98.0455,
          "tp1_touch_rate_pct": 6.74,
          "tp2_hit_rate_pct": 1.49,
          "stop_rate_pct": 3.58,
          "breakeven_rate_pct": 1.07,
          "live_trade_count": 1838,
          "live_expectancy_r": -0.0958,
          "live_profit_factor_r": 0.5844
        }
      ],
      "score_bucket": [
        {
          "score_bucket": "70-80",
          "trade_count": 114,
          "precision_pct": 24.56,
          "expectancy_r": -0.3021,
          "profit_factor_r": 0.2477,
          "avg_win_r": 0.405,
          "avg_loss_r": -0.5323,
          "avg_mae_r": -0.592,
          "worst_mae_r": -2.0073,
          "avg_mfe_r": 0.454,
          "median_score": 77.042,
          "tp1_touch_rate_pct": 16.67,
          "tp2_hit_rate_pct": 3.51,
          "stop_rate_pct": 24.56,
          "breakeven_rate_pct": 10.53,
          "live_trade_count": 55,
          "live_expectancy_r": -0.4297,
          "live_profit_factor_r": 0.2784
        },
        {
          "score_bucket": "90-95",
          "trade_count": 1560,
          "precision_pct": 33.46,
          "expectancy_r": -0.1165,
          "profit_factor_r": 0.4345,
          "avg_win_r": 0.2676,
          "avg_loss_r": -0.3097,
          "avg_mae_r": -0.274,
          "worst_mae_r": -2.4107,
          "avg_mfe_r": 0.26,
          "median_score": 93.437,
          "tp1_touch_rate_pct": 2.18,
          "tp2_hit_rate_pct": 0.13,
          "stop_rate_pct": 1.92,
          "breakeven_rate_pct": 0.0,
          "live_trade_count": 0,
          "live_expectancy_r": 0.0,
          "live_profit_factor_r": 0.0
        },
        {
          "score_bucket": "95-100",
          "trade_count": 4062,
          "precision_pct": 33.92,
          "expectancy_r": -0.0928,
          "profit_factor_r": 0.5456,
          "avg_win_r": 0.3284,
          "avg_loss_r": -0.309,
          "avg_mae_r": -0.286,
          "worst_mae_r": -2.4025,
          "avg_mfe_r": 0.3017,
          "median_score": 98.571,
          "tp1_touch_rate_pct": 4.55,
          "tp2_hit_rate_pct": 0.42,
          "stop_rate_pct": 1.48,
          "breakeven_rate_pct": 0.0,
          "live_trade_count": 4062,
          "live_expectancy_r": -0.0928,
          "live_profit_factor_r": 0.5456
        },
        {
          "score_bucket": "80-90",
          "trade_count": 220,
          "precision_pct": 34.55,
          "expectancy_r": -0.0099,
          "profit_factor_r": 0.9737,
          "avg_win_r": 1.0605,
          "avg_loss_r": -0.5748,
          "avg_mae_r": -0.5711,
          "worst_mae_r": -1.9914,
          "avg_mfe_r": 0.7744,
          "median_score": 83.895,
          "tp1_touch_rate_pct": 29.09,
          "tp2_hit_rate_pct": 16.36,
          "stop_rate_pct": 24.09,
          "breakeven_rate_pct": 10.45,
          "live_trade_count": 128,
          "live_expectancy_r": 0.0802,
          "live_profit_factor_r": 1.1648
        }
      ],
      "volatility_bucket": [
        {
          "volatility_bucket": "low",
          "trade_count": 1842,
          "precision_pct": 31.7,
          "expectancy_r": -0.1331,
          "profit_factor_r": 0.4433,
          "avg_win_r": 0.3342,
          "avg_loss_r": -0.35,
          "avg_mae_r": -0.3141,
          "worst_mae_r": -2.4107,
          "avg_mfe_r": 0.297,
          "median_score": 95.5737,
          "tp1_touch_rate_pct": 4.94,
          "tp2_hit_rate_pct": 0.49,
          "stop_rate_pct": 3.37,
          "breakeven_rate_pct": 0.38,
          "live_trade_count": 1099,
          "live_expectancy_r": -0.1185,
          "live_profit_factor_r": 0.5067
        },
        {
          "volatility_bucket": "mid",
          "trade_count": 2310,
          "precision_pct": 33.42,
          "expectancy_r": -0.104,
          "profit_factor_r": 0.5113,
          "avg_win_r": 0.3255,
          "avg_loss_r": -0.3196,
          "avg_mae_r": -0.3009,
          "worst_mae_r": -2.3423,
          "avg_mfe_r": 0.3107,
          "median_score": 97.157,
          "tp1_touch_rate_pct": 5.19,
          "tp2_hit_rate_pct": 0.78,
          "stop_rate_pct": 2.64,
          "breakeven_rate_pct": 0.78,
          "live_trade_count": 1758,
          "live_expectancy_r": -0.1018,
          "live_profit_factor_r": 0.5347
        },
        {
          "volatility_bucket": "high",
          "trade_count": 1807,
          "precision_pct": 35.86,
          "expectancy_r": -0.0628,
          "profit_factor_r": 0.6769,
          "avg_win_r": 0.3668,
          "avg_loss_r": -0.303,
          "avg_mae_r": -0.2834,
          "worst_mae_r": -1.9914,
          "avg_mfe_r": 0.3258,
          "median_score": 97.8336,
          "tp1_touch_rate_pct": 5.04,
          "tp2_hit_rate_pct": 1.77,
          "stop_rate_pct": 2.82,
          "breakeven_rate_pct": 0.55,
          "live_trade_count": 1390,
          "live_expectancy_r": -0.06,
          "live_profit_factor_r": 0.7002
        }
      ],
      "liquidity_bucket": [
        {
          "liquidity_bucket": "high",
          "trade_count": 5866,
          "precision_pct": 33.6,
          "expectancy_r": -0.1005,
          "profit_factor_r": 0.5333,
          "avg_win_r": 0.3417,
          "avg_loss_r": -0.3243,
          "avg_mae_r": -0.3002,
          "worst_mae_r": -2.4107,
          "avg_mfe_r": 0.3106,
          "median_score": 96.794,
          "tp1_touch_rate_pct": 5.01,
          "tp2_hit_rate_pct": 0.99,
          "stop_rate_pct": 2.95,
          "breakeven_rate_pct": 0.6,
          "live_trade_count": 4191,
          "live_expectancy_r": -0.0915,
          "live_profit_factor_r": 0.5799
        },
        {
          "liquidity_bucket": "mid",
          "trade_count": 91,
          "precision_pct": 36.26,
          "expectancy_r": -0.0907,
          "profit_factor_r": 0.5625,
          "avg_win_r": 0.3214,
          "avg_loss_r": -0.3251,
          "avg_mae_r": -0.2638,
          "worst_mae_r": -1.5959,
          "avg_mfe_r": 0.3487,
          "median_score": 95.8719,
          "tp1_touch_rate_pct": 8.79,
          "tp2_hit_rate_pct": 1.1,
          "stop_rate_pct": 1.1,
          "breakeven_rate_pct": 0.0,
          "live_trade_count": 55,
          "live_expectancy_r": -0.1561,
          "live_profit_factor_r": 0.3577
        }
      ]
    },
    "worst_false_positive_examples": [
      {
        "date": "2023-04-26",
        "ticker": "BBCA",
        "mode": "swing",
        "score": 64.65,
        "regime_status": "risk_off",
        "score_bucket": "60-70",
        "outcome": "stop_loss",
        "realized_r": -1.212595,
        "mae_r": -1.174429,
        "mfe_r": 0.0
      },
      {
        "date": "2023-05-31",
        "ticker": "ICBP",
        "mode": "swing",
        "score": 72.93,
        "regime_status": "risk_off",
        "score_bucket": "70-80",
        "outcome": "stop_loss",
        "realized_r": -1.171382,
        "mae_r": -1.121036,
        "mfe_r": 0.0
      },
      {
        "date": "2023-03-21",
        "ticker": "BBRI",
        "mode": "t1",
        "score": 94.0672,
        "regime_status": "risk_off",
        "score_bucket": "90-95",
        "outcome": "stop_loss",
        "realized_r": -1.168952,
        "mae_r": -1.055826,
        "mfe_r": 0.0
      },
      {
        "date": "2022-04-11",
        "ticker": "TPIA",
        "mode": "swing",
        "score": 72.68,
        "regime_status": "risk_off",
        "score_bucket": "70-80",
        "outcome": "stop_loss",
        "realized_r": -1.160237,
        "mae_r": -1.11134,
        "mfe_r": 0.185223
      },
      {
        "date": "2023-03-13",
        "ticker": "BMRI",
        "mode": "t1",
        "score": 77.077,
        "regime_status": "risk_off",
        "score_bucket": "70-80",
        "outcome": "stop_loss",
        "realized_r": -1.159672,
        "mae_r": -1.313785,
        "mfe_r": 0.0
      },
      {
        "date": "2024-11-08",
        "ticker": "UNTR",
        "mode": "t1",
        "score": 90.4422,
        "regime_status": "risk_off",
        "score_bucket": "90-95",
        "outcome": "stop_loss",
        "realized_r": -1.154907,
        "mae_r": -1.298418,
        "mfe_r": 0.0
      },
      {
        "date": "2026-01-28",
        "ticker": "INDF",
        "mode": "t1",
        "score": 92.0952,
        "regime_status": "risk_off",
        "score_bucket": "90-95",
        "outcome": "stop_loss",
        "realized_r": -1.148928,
        "mae_r": -2.410663,
        "mfe_r": 0.0
      },
      {
        "date": "2022-02-10",
        "ticker": "TPIA",
        "mode": "swing",
        "score": 82.33,
        "regime_status": "risk_off",
        "score_bucket": "80-90",
        "outcome": "stop_loss",
        "realized_r": -1.145266,
        "mae_r": -1.725823,
        "mfe_r": 0.057527
      },
      {
        "date": "2022-02-09",
        "ticker": "TPIA",
        "mode": "swing",
        "score": 85.29,
        "regime_status": "risk_off",
        "score_bucket": "80-90",
        "outcome": "stop_loss",
        "realized_r": -1.142558,
        "mae_r": -1.211383,
        "mfe_r": 0.576849
      },
      {
        "date": "2022-10-26",
        "ticker": "ICBP",
        "mode": "swing",
        "score": 69.18,
        "regime_status": "risk_on",
        "score_bucket": "60-70",
        "outcome": "stop_loss",
        "realized_r": -1.13958,
        "mae_r": -1.095004,
        "mfe_r": 0.243334
      },
      {
        "date": "2021-08-30",
        "ticker": "INDF",
        "mode": "t1",
        "score": 94.9299,
        "regime_status": "risk_off",
        "score_bucket": "90-95",
        "outcome": "stop_loss",
        "realized_r": -1.138146,
        "mae_r": -1.266308,
        "mfe_r": 0.0
      },
      {
        "date": "2022-10-19",
        "ticker": "UNVR",
        "mode": "swing",
        "score": 70.42,
        "regime_status": "risk_off",
        "score_bucket": "70-80",
        "outcome": "stop_loss",
        "realized_r": -1.136561,
        "mae_r": -1.614413,
        "mfe_r": 0.54541
      },
      {
        "date": "2026-05-29",
        "ticker": "INDF",
        "mode": "t1",
        "score": 92.9028,
        "regime_status": "risk_off",
        "score_bucket": "90-95",
        "outcome": "stop_loss",
        "realized_r": -1.134977,
        "mae_r": -1.166475,
        "mfe_r": 0.0
      },
      {
        "date": "2024-10-31",
        "ticker": "CPIN",
        "mode": "t1",
        "score": 91.7689,
        "regime_status": "risk_off",
        "score_bucket": "90-95",
        "outcome": "stop_loss",
        "realized_r": -1.132989,
        "mae_r": -1.68987,
        "mfe_r": 0.0
      },
      {
        "date": "2025-12-04",
        "ticker": "UNTR",
        "mode": "swing",
        "score": 69.71,
        "regime_status": "risk_off",
        "score_bucket": "60-70",
        "outcome": "stop_loss",
        "realized_r": -1.132695,
        "mae_r": -1.09148,
        "mfe_r": 0.240496
      },
      {
        "date": "2024-02-07",
        "ticker": "UNVR",
        "mode": "t1",
        "score": 95.6599,
        "regime_status": "risk_off",
        "score_bucket": "95-100",
        "outcome": "stop_loss",
        "realized_r": -1.131177,
        "mae_r": -2.402502,
        "mfe_r": 0.0
      },
      {
        "date": "2022-10-17",
        "ticker": "PTBA",
        "mode": "t1",
        "score": 92.2829,
        "regime_status": "risk_off",
        "score_bucket": "90-95",
        "outcome": "stop_loss",
        "realized_r": -1.131046,
        "mae_r": -1.530133,
        "mfe_r": 0.15829
      },
      {
        "date": "2025-12-05",
        "ticker": "UNTR",
        "mode": "t1",
        "score": 100.0,
        "regime_status": "risk_off",
        "score_bucket": "95-100",
        "outcome": "stop_loss",
        "realized_r": -1.130299,
        "mae_r": -1.192696,
        "mfe_r": 0.0
      },
      {
        "date": "2022-10-20",
        "ticker": "UNVR",
        "mode": "swing",
        "score": 71.26,
        "regime_status": "risk_off",
        "score_bucket": "70-80",
        "outcome": "stop_loss",
        "realized_r": -1.128768,
        "mae_r": -1.71458,
        "mfe_r": 0.306175
      },
      {
        "date": "2023-03-27",
        "ticker": "BBNI",
        "mode": "t1",
        "score": 96.3865,
        "regime_status": "risk_off",
        "score_bucket": "95-100",
        "outcome": "stop_loss",
        "realized_r": -1.127988,
        "mae_r": -1.1534,
        "mfe_r": 0.0
      }
    ]
  },
  "by_ticker_preview": [
    {
      "ticker": "ICBP",
      "candidate_count": 224,
      "v1_live_count": 45,
      "v2_recommended_count": 93,
      "v2_recommended_rate_pct": 41.52,
      "all_precision_pct": 31.7,
      "all_expectancy_r": -0.2289,
      "all_profit_factor_r": 0.4227,
      "v2_precision_pct": 24.73,
      "v2_expectancy_r": -0.2499,
      "v2_profit_factor_r": 0.1514,
      "v2_avg_mae_r": -0.3794,
      "v2_avg_mfe_r": 0.154
    },
    {
      "ticker": "BBCA",
      "candidate_count": 116,
      "v1_live_count": 16,
      "v2_recommended_count": 38,
      "v2_recommended_rate_pct": 32.76,
      "all_precision_pct": 28.45,
      "all_expectancy_r": -0.3098,
      "all_profit_factor_r": 0.2895,
      "v2_precision_pct": 23.68,
      "v2_expectancy_r": -0.2241,
      "v2_profit_factor_r": 0.178,
      "v2_avg_mae_r": -0.3046,
      "v2_avg_mfe_r": 0.2066
    },
    {
      "ticker": "INDF",
      "candidate_count": 228,
      "v1_live_count": 32,
      "v2_recommended_count": 75,
      "v2_recommended_rate_pct": 32.89,
      "all_precision_pct": 36.84,
      "all_expectancy_r": -0.2013,
      "all_profit_factor_r": 0.4912,
      "v2_precision_pct": 30.67,
      "v2_expectancy_r": -0.2143,
      "v2_profit_factor_r": 0.1817,
      "v2_avg_mae_r": -0.3594,
      "v2_avg_mfe_r": 0.166
    },
    {
      "ticker": "BBRI",
      "candidate_count": 190,
      "v1_live_count": 57,
      "v2_recommended_count": 98,
      "v2_recommended_rate_pct": 51.58,
      "all_precision_pct": 32.11,
      "all_expectancy_r": -0.1524,
      "all_profit_factor_r": 0.5416,
      "v2_precision_pct": 26.53,
      "v2_expectancy_r": -0.2071,
      "v2_profit_factor_r": 0.2219,
      "v2_avg_mae_r": -0.3057,
      "v2_avg_mfe_r": 0.2296
    },
    {
      "ticker": "ASII",
      "candidate_count": 174,
      "v1_live_count": 51,
      "v2_recommended_count": 87,
      "v2_recommended_rate_pct": 50.0,
      "all_precision_pct": 27.01,
      "all_expectancy_r": -0.2194,
      "all_profit_factor_r": 0.3982,
      "v2_precision_pct": 24.14,
      "v2_expectancy_r": -0.1933,
      "v2_profit_factor_r": 0.2198,
      "v2_avg_mae_r": -0.3391,
      "v2_avg_mfe_r": 0.1824
    },
    {
      "ticker": "AKRA",
      "candidate_count": 357,
      "v1_live_count": 144,
      "v2_recommended_count": 200,
      "v2_recommended_rate_pct": 56.02,
      "all_precision_pct": 29.97,
      "all_expectancy_r": -0.2314,
      "all_profit_factor_r": 0.3662,
      "v2_precision_pct": 28.0,
      "v2_expectancy_r": -0.1905,
      "v2_profit_factor_r": 0.2323,
      "v2_avg_mae_r": -0.3121,
      "v2_avg_mfe_r": 0.2329
    },
    {
      "ticker": "TLKM",
      "candidate_count": 233,
      "v1_live_count": 74,
      "v2_recommended_count": 130,
      "v2_recommended_rate_pct": 55.79,
      "all_precision_pct": 34.33,
      "all_expectancy_r": -0.1453,
      "all_profit_factor_r": 0.5256,
      "v2_precision_pct": 29.23,
      "v2_expectancy_r": -0.184,
      "v2_profit_factor_r": 0.2882,
      "v2_avg_mae_r": -0.3195,
      "v2_avg_mfe_r": 0.2186
    },
    {
      "ticker": "KLBF",
      "candidate_count": 257,
      "v1_live_count": 75,
      "v2_recommended_count": 120,
      "v2_recommended_rate_pct": 46.69,
      "all_precision_pct": 28.79,
      "all_expectancy_r": -0.2293,
      "all_profit_factor_r": 0.3897,
      "v2_precision_pct": 28.33,
      "v2_expectancy_r": -0.1797,
      "v2_profit_factor_r": 0.2624,
      "v2_avg_mae_r": -0.3336,
      "v2_avg_mfe_r": 0.2299
    },
    {
      "ticker": "MIKA",
      "candidate_count": 220,
      "v1_live_count": 99,
      "v2_recommended_count": 148,
      "v2_recommended_rate_pct": 67.27,
      "all_precision_pct": 25.91,
      "all_expectancy_r": -0.26,
      "all_profit_factor_r": 0.2469,
      "v2_precision_pct": 27.03,
      "v2_expectancy_r": -0.1706,
      "v2_profit_factor_r": 0.267,
      "v2_avg_mae_r": -0.3276,
      "v2_avg_mfe_r": 0.2443
    },
    {
      "ticker": "CPIN",
      "candidate_count": 213,
      "v1_live_count": 72,
      "v2_recommended_count": 120,
      "v2_recommended_rate_pct": 56.34,
      "all_precision_pct": 24.41,
      "all_expectancy_r": -0.3473,
      "all_profit_factor_r": 0.2169,
      "v2_precision_pct": 30.0,
      "v2_expectancy_r": -0.1411,
      "v2_profit_factor_r": 0.37,
      "v2_avg_mae_r": -0.3228,
      "v2_avg_mfe_r": 0.2473
    },
    {
      "ticker": "BMRI",
      "candidate_count": 246,
      "v1_live_count": 65,
      "v2_recommended_count": 100,
      "v2_recommended_rate_pct": 40.65,
      "all_precision_pct": 39.84,
      "all_expectancy_r": -0.0655,
      "all_profit_factor_r": 0.8091,
      "v2_precision_pct": 36.0,
      "v2_expectancy_r": -0.1388,
      "v2_profit_factor_r": 0.3944,
      "v2_avg_mae_r": -0.2913,
      "v2_avg_mfe_r": 0.2686
    },
    {
      "ticker": "UNTR",
      "candidate_count": 309,
      "v1_live_count": 105,
      "v2_recommended_count": 163,
      "v2_recommended_rate_pct": 52.75,
      "all_precision_pct": 34.95,
      "all_expectancy_r": -0.1262,
      "all_profit_factor_r": 0.6253,
      "v2_precision_pct": 30.67,
      "v2_expectancy_r": -0.1353,
      "v2_profit_factor_r": 0.4255,
      "v2_avg_mae_r": -0.2896,
      "v2_avg_mfe_r": 0.2918
    },
    {
      "ticker": "SIDO",
      "candidate_count": 242,
      "v1_live_count": 80,
      "v2_recommended_count": 116,
      "v2_recommended_rate_pct": 47.93,
      "all_precision_pct": 32.64,
      "all_expectancy_r": -0.2287,
      "all_profit_factor_r": 0.3438,
      "v2_precision_pct": 33.62,
      "v2_expectancy_r": -0.1345,
      "v2_profit_factor_r": 0.417,
      "v2_avg_mae_r": -0.3326,
      "v2_avg_mfe_r": 0.3169
    },
    {
      "ticker": "SMRA",
      "candidate_count": 189,
      "v1_live_count": 106,
      "v2_recommended_count": 133,
      "v2_recommended_rate_pct": 70.37,
      "all_precision_pct": 31.22,
      "all_expectancy_r": -0.2332,
      "all_profit_factor_r": 0.2681,
      "v2_precision_pct": 33.83,
      "v2_expectancy_r": -0.1332,
      "v2_profit_factor_r": 0.3443,
      "v2_avg_mae_r": -0.2922,
      "v2_avg_mfe_r": 0.2462
    },
    {
      "ticker": "BBNI",
      "candidate_count": 240,
      "v1_live_count": 99,
      "v2_recommended_count": 128,
      "v2_recommended_rate_pct": 53.33,
      "all_precision_pct": 27.92,
      "all_expectancy_r": -0.2126,
      "all_profit_factor_r": 0.4084,
      "v2_precision_pct": 33.59,
      "v2_expectancy_r": -0.1294,
      "v2_profit_factor_r": 0.4619,
      "v2_avg_mae_r": -0.3001,
      "v2_avg_mfe_r": 0.3226
    },
    {
      "ticker": "BBTN",
      "candidate_count": 224,
      "v1_live_count": 125,
      "v2_recommended_count": 124,
      "v2_recommended_rate_pct": 55.36,
      "all_precision_pct": 29.91,
      "all_expectancy_r": -0.2472,
      "all_profit_factor_r": 0.4119,
      "v2_precision_pct": 33.06,
      "v2_expectancy_r": -0.1269,
      "v2_profit_factor_r": 0.4428,
      "v2_avg_mae_r": -0.2939,
      "v2_avg_mfe_r": 0.2697
    },
    {
      "ticker": "ARTO",
      "candidate_count": 251,
      "v1_live_count": 120,
      "v2_recommended_count": 134,
      "v2_recommended_rate_pct": 53.39,
      "all_precision_pct": 34.26,
      "all_expectancy_r": -0.0928,
      "all_profit_factor_r": 0.6748,
      "v2_precision_pct": 32.09,
      "v2_expectancy_r": -0.1178,
      "v2_profit_factor_r": 0.4426,
      "v2_avg_mae_r": -0.2913,
      "v2_avg_mfe_r": 0.2748
    },
    {
      "ticker": "ITMG",
      "candidate_count": 320,
      "v1_live_count": 147,
      "v2_recommended_count": 162,
      "v2_recommended_rate_pct": 50.62,
      "all_precision_pct": 34.38,
      "all_expectancy_r": -0.1265,
      "all_profit_factor_r": 0.6902,
      "v2_precision_pct": 36.42,
      "v2_expectancy_r": -0.116,
      "v2_profit_factor_r": 0.5566,
      "v2_avg_mae_r": -0.3342,
      "v2_avg_mfe_r": 0.3952
    },
    {
      "ticker": "EXCL",
      "candidate_count": 304,
      "v1_live_count": 135,
      "v2_recommended_count": 171,
      "v2_recommended_rate_pct": 56.25,
      "all_precision_pct": 29.28,
      "all_expectancy_r": -0.1057,
      "all_profit_factor_r": 0.6147,
      "v2_precision_pct": 28.65,
      "v2_expectancy_r": -0.114,
      "v2_profit_factor_r": 0.4458,
      "v2_avg_mae_r": -0.3108,
      "v2_avg_mfe_r": 0.2944
    },
    {
      "ticker": "BRIS",
      "candidate_count": 299,
      "v1_live_count": 116,
      "v2_recommended_count": 141,
      "v2_recommended_rate_pct": 47.16,
      "all_precision_pct": 37.12,
      "all_expectancy_r": -0.0683,
      "all_profit_factor_r": 0.7557,
      "v2_precision_pct": 35.46,
      "v2_expectancy_r": -0.1111,
      "v2_profit_factor_r": 0.4662,
      "v2_avg_mae_r": -0.2762,
      "v2_avg_mfe_r": 0.3085
    }
  ],
  "by_regime": [
    {
      "mode": "swing",
      "regime_status": "risk_off",
      "candidate_count": 3550,
      "v1_live_count": 447,
      "v2_recommended_count": 75,
      "v2_recommended_rate_pct": 2.11,
      "all_precision_pct": 34.85,
      "all_expectancy_r": -0.1432,
      "all_profit_factor_r": 0.6911,
      "v2_precision_pct": 30.67,
      "v2_expectancy_r": -0.1088,
      "v2_profit_factor_r": 0.7894,
      "v2_avg_mae_r": -0.8132,
      "v2_avg_mfe_r": 0.9176
    },
    {
      "mode": "t1",
      "regime_status": "risk_off",
      "candidate_count": 3930,
      "v1_live_count": 2335,
      "v2_recommended_count": 3733,
      "v2_recommended_rate_pct": 94.99,
      "all_precision_pct": 33.21,
      "all_expectancy_r": -0.1059,
      "all_profit_factor_r": 0.486,
      "v2_precision_pct": 33.32,
      "v2_expectancy_r": -0.1047,
      "v2_profit_factor_r": 0.4878,
      "v2_avg_mae_r": -0.2853,
      "v2_avg_mfe_r": 0.2756
    },
    {
      "mode": "t1",
      "regime_status": "risk_on",
      "candidate_count": 2040,
      "v1_live_count": 1727,
      "v2_recommended_count": 2040,
      "v2_recommended_rate_pct": 100.0,
      "all_precision_pct": 34.66,
      "all_expectancy_r": -0.0936,
      "all_profit_factor_r": 0.5465,
      "v2_precision_pct": 34.66,
      "v2_expectancy_r": -0.0936,
      "v2_profit_factor_r": 0.5465,
      "v2_avg_mae_r": -0.2797,
      "v2_avg_mfe_r": 0.3131
    },
    {
      "mode": "swing",
      "regime_status": "risk_on",
      "candidate_count": 2040,
      "v1_live_count": 581,
      "v2_recommended_count": 111,
      "v2_recommended_rate_pct": 5.44,
      "all_precision_pct": 31.96,
      "all_expectancy_r": -0.1782,
      "all_profit_factor_r": 0.6453,
      "v2_precision_pct": 27.03,
      "v2_expectancy_r": -0.0783,
      "v2_profit_factor_r": 0.8547,
      "v2_avg_mae_r": -0.802,
      "v2_avg_mfe_r": 1.0556
    }
  ],
  "threshold_candidates_preview": [
    {
      "mode": "swing",
      "threshold": 0.7,
      "trade_count": 5,
      "selection_rate_pct": 0.09,
      "precision_pct": 60.0,
      "expectancy_r": 0.6492,
      "profit_factor_r": 2.4352,
      "avg_win_r": 1.8358,
      "avg_loss_r": -1.1308,
      "avg_mae_r": -0.6347,
      "avg_mfe_r": 1.5887
    },
    {
      "mode": "swing",
      "threshold": 0.65,
      "trade_count": 12,
      "selection_rate_pct": 0.21,
      "precision_pct": 41.67,
      "expectancy_r": 0.2489,
      "profit_factor_r": 1.4773,
      "avg_win_r": 1.8492,
      "avg_loss_r": -0.8941,
      "avg_mae_r": -0.7272,
      "avg_mfe_r": 1.2605
    },
    {
      "mode": "swing",
      "threshold": 0.6,
      "trade_count": 56,
      "selection_rate_pct": 1.0,
      "precision_pct": 37.5,
      "expectancy_r": 0.0718,
      "profit_factor_r": 1.1469,
      "avg_win_r": 1.4953,
      "avg_loss_r": -0.7823,
      "avg_mae_r": -0.7275,
      "avg_mfe_r": 1.0873
    },
    {
      "mode": "swing",
      "threshold": 0.75,
      "trade_count": 0,
      "selection_rate_pct": 0.0,
      "precision_pct": 0.0,
      "expectancy_r": 0.0,
      "profit_factor_r": 0.0,
      "avg_win_r": 0.0,
      "avg_loss_r": 0.0,
      "avg_mae_r": 0.0,
      "avg_mfe_r": 0.0
    },
    {
      "mode": "swing",
      "threshold": 0.55,
      "trade_count": 186,
      "selection_rate_pct": 3.33,
      "precision_pct": 28.49,
      "expectancy_r": -0.0906,
      "profit_factor_r": 0.8291,
      "avg_win_r": 1.5417,
      "avg_loss_r": -0.7411,
      "avg_mae_r": -0.8065,
      "avg_mfe_r": 1.0
    },
    {
      "mode": "swing",
      "threshold": 0.52,
      "trade_count": 362,
      "selection_rate_pct": 6.48,
      "precision_pct": 29.28,
      "expectancy_r": -0.1036,
      "profit_factor_r": 0.8013,
      "avg_win_r": 1.4277,
      "avg_loss_r": -0.7377,
      "avg_mae_r": -0.7806,
      "avg_mfe_r": 0.9827
    },
    {
      "mode": "swing",
      "threshold": 0.5,
      "trade_count": 509,
      "selection_rate_pct": 9.11,
      "precision_pct": 28.09,
      "expectancy_r": -0.1402,
      "profit_factor_r": 0.7416,
      "avg_win_r": 1.4321,
      "avg_loss_r": -0.7545,
      "avg_mae_r": -0.789,
      "avg_mfe_r": 0.9632
    },
    {
      "mode": "swing",
      "threshold": 0.45,
      "trade_count": 1176,
      "selection_rate_pct": 21.04,
      "precision_pct": 30.61,
      "expectancy_r": -0.1692,
      "profit_factor_r": 0.6812,
      "avg_win_r": 1.1813,
      "avg_loss_r": -0.7651,
      "avg_mae_r": -0.7973,
      "avg_mfe_r": 0.8878
    },
    {
      "mode": "t1",
      "threshold": 0.65,
      "trade_count": 5647,
      "selection_rate_pct": 94.59,
      "precision_pct": 33.79,
      "expectancy_r": -0.1001,
      "profit_factor_r": 0.5121,
      "avg_win_r": 0.311,
      "avg_loss_r": -0.3099,
      "avg_mae_r": -0.2831,
      "avg_mfe_r": 0.2897
    },
    {
      "mode": "t1",
      "threshold": 0.45,
      "trade_count": 5785,
      "selection_rate_pct": 96.9,
      "precision_pct": 33.85,
      "expectancy_r": -0.1005,
      "profit_factor_r": 0.5098,
      "avg_win_r": 0.3087,
      "avg_loss_r": -0.3098,
      "avg_mae_r": -0.2831,
      "avg_mfe_r": 0.2889
    },
    {
      "mode": "t1",
      "threshold": 0.5,
      "trade_count": 5780,
      "selection_rate_pct": 96.82,
      "precision_pct": 33.82,
      "expectancy_r": -0.1006,
      "profit_factor_r": 0.5095,
      "avg_win_r": 0.3089,
      "avg_loss_r": -0.3099,
      "avg_mae_r": -0.2833,
      "avg_mfe_r": 0.2889
    },
    {
      "mode": "t1",
      "threshold": 0.55,
      "trade_count": 5755,
      "selection_rate_pct": 96.4,
      "precision_pct": 33.78,
      "expectancy_r": -0.1008,
      "profit_factor_r": 0.5093,
      "avg_win_r": 0.3096,
      "avg_loss_r": -0.3101,
      "avg_mae_r": -0.2835,
      "avg_mfe_r": 0.2891
    },
    {
      "mode": "t1",
      "threshold": 0.52,
      "trade_count": 5773,
      "selection_rate_pct": 96.7,
      "precision_pct": 33.8,
      "expectancy_r": -0.1008,
      "profit_factor_r": 0.5087,
      "avg_win_r": 0.3088,
      "avg_loss_r": -0.3099,
      "avg_mae_r": -0.2834,
      "avg_mfe_r": 0.2889
    },
    {
      "mode": "t1",
      "threshold": 0.75,
      "trade_count": 3202,
      "selection_rate_pct": 53.63,
      "precision_pct": 33.6,
      "expectancy_r": -0.1012,
      "profit_factor_r": 0.5323,
      "avg_win_r": 0.3428,
      "avg_loss_r": -0.3259,
      "avg_mae_r": -0.2969,
      "avg_mfe_r": 0.3109
    },
    {
      "mode": "t1",
      "threshold": 0.6,
      "trade_count": 5727,
      "selection_rate_pct": 95.93,
      "precision_pct": 33.7,
      "expectancy_r": -0.1013,
      "profit_factor_r": 0.5079,
      "avg_win_r": 0.3102,
      "avg_loss_r": -0.3104,
      "avg_mae_r": -0.2839,
      "avg_mfe_r": 0.2891
    },
    {
      "mode": "t1",
      "threshold": 0.7,
      "trade_count": 5055,
      "selection_rate_pct": 84.67,
      "precision_pct": 33.63,
      "expectancy_r": -0.1014,
      "profit_factor_r": 0.5124,
      "avg_win_r": 0.3169,
      "avg_loss_r": -0.3134,
      "avg_mae_r": -0.2865,
      "avg_mfe_r": 0.2923
    }
  ],
  "recent_v2_recommended": [
    {
      "date": "2026-07-15",
      "exit_date": "2026-07-16",
      "ticker": "UNTR",
      "mode": "t1",
      "rank": 3,
      "score": 100.0,
      "predicted_p_win": 0.7842,
      "predicted_p_win_source": "shadow_p_win",
      "passes_live_threshold": true,
      "horizon_days": 1,
      "bars_to_exit": 1,
      "entry": 27300.0,
      "stop": 25532.7355,
      "tp1": 29067.2645,
      "tp2": 30834.529,
      "exit_price": 27025.0,
      "outcome": "horizon_exit",
      "win": false,
      "tp1_touched": false,
      "tp2_touched": false,
      "realized_r": -0.247749,
      "return_pct": -1.6038,
      "mae_r": -0.226338,
      "mfe_r": 0.0,
      "atr_pct": 3.2367,
      "avg_vol_20d": 4722745.0,
      "ret_20d_pct": 18.6957,
      "liquidity_bucket": "high",
      "score_bucket": "95-100",
      "decay_1d_r": -0.247749,
      "decay_2d_r": null,
      "decay_3d_r": null,
      "v1_rank": 3,
      "v2_rank": 1,
      "shadow_p_win": 0.7842,
      "shadow_expected_r": 0.9605,
      "shadow_threshold": 0.52,
      "v2_recommended": true,
      "shadow_model_source": "fallback",
      "shadow_market_regime": "risk_off",
      "regime_status": "risk_off",
      "volatility_bucket": "mid"
    },
    {
      "date": "2026-07-15",
      "exit_date": "2026-07-16",
      "ticker": "ANTM",
      "mode": "t1",
      "rank": 1,
      "score": 100.0,
      "predicted_p_win": 0.75,
      "predicted_p_win_source": "shadow_p_win",
      "passes_live_threshold": true,
      "horizon_days": 1,
      "bars_to_exit": 1,
      "entry": 3070.0,
      "stop": 2772.2099,
      "tp1": 3367.7901,
      "tp2": 3665.5801,
      "exit_price": 3070.0,
      "outcome": "horizon_exit",
      "win": false,
      "tp1_touched": false,
      "tp2_touched": false,
      "realized_r": -0.061856,
      "return_pct": -0.6,
      "mae_r": -0.100742,
      "mfe_r": 0.033581,
      "atr_pct": 4.85,
      "avg_vol_20d": 95007405.0,
      "ret_20d_pct": -2.8481,
      "liquidity_bucket": "high",
      "score_bucket": "95-100",
      "decay_1d_r": -0.061856,
      "decay_2d_r": null,
      "decay_3d_r": null,
      "v1_rank": 1,
      "v2_rank": 2,
      "shadow_p_win": 0.75,
      "shadow_expected_r": 0.875,
      "shadow_threshold": 0.52,
      "v2_recommended": true,
      "shadow_model_source": "fallback",
      "shadow_market_regime": "risk_off",
      "regime_status": "risk_off",
      "volatility_bucket": "high"
    },
    {
      "date": "2026-07-15",
      "exit_date": "2026-07-16",
      "ticker": "ESSA",
      "mode": "t1",
      "rank": 2,
      "score": 100.0,
      "predicted_p_win": 0.75,
      "predicted_p_win_source": "shadow_p_win",
      "passes_live_threshold": true,
      "horizon_days": 1,
      "bars_to_exit": 1,
      "entry": 600.0,
      "stop": 528.4298,
      "tp1": 671.5702,
      "tp2": 743.1404,
      "exit_price": 595.0,
      "outcome": "horizon_exit",
      "win": false,
      "tp1_touched": false,
      "tp2_touched": false,
      "realized_r": -0.119917,
      "return_pct": -1.430417,
      "mae_r": -0.069861,
      "mfe_r": 0.139723,
      "atr_pct": 5.9642,
      "avg_vol_20d": 81952120.0,
      "ret_20d_pct": -9.7744,
      "liquidity_bucket": "high",
      "score_bucket": "95-100",
      "decay_1d_r": -0.119917,
      "decay_2d_r": null,
      "decay_3d_r": null,
      "v1_rank": 2,
      "v2_rank": 3,
      "shadow_p_win": 0.75,
      "shadow_expected_r": 0.875,
      "shadow_threshold": 0.52,
      "v2_recommended": true,
      "shadow_model_source": "fallback",
      "shadow_market_regime": "risk_off",
      "regime_status": "risk_off",
      "volatility_bucket": "high"
    },
    {
      "date": "2026-07-15",
      "exit_date": "2026-07-16",
      "ticker": "HRUM",
      "mode": "t1",
      "rank": 4,
      "score": 99.417,
      "predicted_p_win": 0.7442,
      "predicted_p_win_source": "shadow_p_win",
      "passes_live_threshold": true,
      "horizon_days": 1,
      "bars_to_exit": 1,
      "entry": 795.0,
      "stop": 714.2418,
      "tp1": 875.7582,
      "tp2": 956.5164,
      "exit_price": 790.0,
      "outcome": "horizon_exit",
      "win": false,
      "tp1_touched": false,
      "tp2_touched": false,
      "realized_r": -0.120762,
      "return_pct": -1.22673,
      "mae_r": -0.061913,
      "mfe_r": 0.061913,
      "atr_pct": 5.0791,
      "avg_vol_20d": 5742870.0,
      "ret_20d_pct": -1.8519,
      "liquidity_bucket": "high",
      "score_bucket": "95-100",
      "decay_1d_r": -0.120762,
      "decay_2d_r": null,
      "decay_3d_r": null,
      "v1_rank": 4,
      "v2_rank": 4,
      "shadow_p_win": 0.7442,
      "shadow_expected_r": 0.8605,
      "shadow_threshold": 0.52,
      "v2_recommended": true,
      "shadow_model_source": "fallback",
      "shadow_market_regime": "risk_off",
      "regime_status": "risk_off",
      "volatility_bucket": "high"
    },
    {
      "date": "2026-07-15",
      "exit_date": "2026-07-16",
      "ticker": "INCO",
      "mode": "t1",
      "rank": 5,
      "score": 99.1351,
      "predicted_p_win": 0.7414,
      "predicted_p_win_source": "shadow_p_win",
      "passes_live_threshold": true,
      "horizon_days": 1,
      "bars_to_exit": 1,
      "entry": 4900.0,
      "stop": 4371.6846,
      "tp1": 5428.3154,
      "tp2": 5956.6308,
      "exit_price": 4890.0,
      "outcome": "horizon_exit",
      "win": false,
      "tp1_touched": false,
      "tp2_touched": false,
      "realized_r": -0.07451,
      "return_pct": -0.803367,
      "mae_r": -0.037856,
      "mfe_r": 0.075712,
      "atr_pct": 5.391,
      "avg_vol_20d": 11351460.0,
      "ret_20d_pct": -1.8036,
      "liquidity_bucket": "high",
      "score_bucket": "95-100",
      "decay_1d_r": -0.07451,
      "decay_2d_r": null,
      "decay_3d_r": null,
      "v1_rank": 5,
      "v2_rank": 5,
      "shadow_p_win": 0.7414,
      "shadow_expected_r": 0.8535,
      "shadow_threshold": 0.52,
      "v2_recommended": true,
      "shadow_model_source": "fallback",
      "shadow_market_regime": "risk_off",
      "regime_status": "risk_off",
      "volatility_bucket": "high"
    },
    {
      "date": "2026-07-14",
      "exit_date": "2026-07-15",
      "ticker": "ITMG",
      "mode": "t1",
      "rank": 5,
      "score": 96.4408,
      "predicted_p_win": 0.8128,
      "predicted_p_win_source": "shadow_p_win",
      "passes_live_threshold": true,
      "horizon_days": 1,
      "bars_to_exit": 1,
      "entry": 24000.0,
      "stop": 22908.5114,
      "tp1": 25091.4886,
      "tp2": 26182.9773,
      "exit_price": 24025.0,
      "outcome": "horizon_exit",
      "win": false,
      "tp1_touched": false,
      "tp2_touched": false,
      "realized_r": -0.109106,
      "return_pct": -0.496198,
      "mae_r": -0.137427,
      "mfe_r": 0.091618,
      "atr_pct": 2.2739,
      "avg_vol_20d": 1113670.0,
      "ret_20d_pct": 2.6738,
      "liquidity_bucket": "mid",
      "score_bucket": "95-100",
      "decay_1d_r": -0.109106,
      "decay_2d_r": -0.177579,
      "decay_3d_r": null,
      "v1_rank": 5,
      "v2_rank": 1,
      "shadow_p_win": 0.8128,
      "shadow_expected_r": 1.032,
      "shadow_threshold": 0.52,
      "v2_recommended": true,
      "shadow_model_source": "fallback",
      "shadow_market_regime": "risk_off",
      "regime_status": "risk_off",
      "volatility_bucket": "low"
    },
    {
      "date": "2026-07-14",
      "exit_date": "2026-07-15",
      "ticker": "UNTR",
      "mode": "t1",
      "rank": 2,
      "score": 100.0,
      "predicted_p_win": 0.7884,
      "predicted_p_win_source": "shadow_p_win",
      "passes_live_threshold": true,
      "horizon_days": 1,
      "bars_to_exit": 1,
      "entry": 27500.0,
      "stop": 25754.4844,
      "tp1": 29245.5156,
      "tp2": 30991.0313,
      "exit_price": 27300.0,
      "outcome": "horizon_exit",
      "win": false,
      "tp1_touched": false,
      "tp2_touched": false,
      "realized_r": -0.208706,
      "return_pct": -1.324727,
      "mae_r": -0.558574,
      "mfe_r": 0.028645,
      "atr_pct": 3.1737,
      "avg_vol_20d": 4768640.0,
      "ret_20d_pct": 20.8791,
      "liquidity_bucket": "high",
      "score_bucket": "95-100",
      "decay_1d_r": -0.208706,
      "decay_2d_r": -0.365701,
      "decay_3d_r": null,
      "v1_rank": 2,
      "v2_rank": 2,
      "shadow_p_win": 0.7884,
      "shadow_expected_r": 0.971,
      "shadow_threshold": 0.52,
      "v2_recommended": true,
      "shadow_model_source": "fallback",
      "shadow_market_regime": "risk_off",
      "regime_status": "risk_off",
      "volatility_bucket": "mid"
    },
    {
      "date": "2026-07-14",
      "exit_date": "2026-07-15",
      "ticker": "ADRO",
      "mode": "t1",
      "rank": 3,
      "score": 97.7201,
      "predicted_p_win": 0.787,
      "predicted_p_win_source": "shadow_p_win",
      "passes_live_threshold": true,
      "horizon_days": 1,
      "bars_to_exit": 1,
      "entry": 2480.0,
      "stop": 2338.518,
      "tp1": 2621.482,
      "tp2": 2762.9641,
      "exit_price": 2490.0,
      "outcome": "horizon_exit",
      "win": false,
      "tp1_touched": false,
      "tp2_touched": false,
      "realized_r": -0.034739,
      "return_pct": -0.198185,
      "mae_r": -0.212041,
      "mfe_r": 0.282721,
      "atr_pct": 2.8525,
      "avg_vol_20d": 30988695.0,
      "ret_20d_pct": 6.8966,
      "liquidity_bucket": "high",
      "score_bucket": "95-100",
      "decay_1d_r": -0.034739,
      "decay_2d_r": -0.316471,
      "decay_3d_r": null,
      "v1_rank": 3,
      "v2_rank": 3,
      "shadow_p_win": 0.787,
      "shadow_expected_r": 0.9675,
      "shadow_threshold": 0.52,
      "v2_recommended": true,
      "shadow_model_source": "fallback",
      "shadow_market_regime": "risk_off",
      "regime_status": "risk_off",
      "volatility_bucket": "low"
    },
    {
      "date": "2026-07-14",
      "exit_date": "2026-07-15",
      "ticker": "MEDC",
      "mode": "t1",
      "rank": 1,
      "score": 100.0,
      "predicted_p_win": 0.75,
      "predicted_p_win_source": "shadow_p_win",
      "passes_live_threshold": true,
      "horizon_days": 1,
      "bars_to_exit": 1,
      "entry": 1250.0,
      "stop": 1133.4911,
      "tp1": 1366.5089,
      "tp2": 1483.0179,
      "exit_price": 1235.0,
      "outcome": "horizon_exit",
      "win": false,
      "tp1_touched": false,
      "tp2_touched": false,
      "realized_r": -0.192668,
      "return_pct": -1.7958,
      "mae_r": -0.343321,
      "mfe_r": 0.0,
      "atr_pct": 4.6604,
      "avg_vol_20d": 46186840.0,
      "ret_20d_pct": 5.9322,
      "liquidity_bucket": "high",
      "score_bucket": "95-100",
      "decay_1d_r": -0.192668,
      "decay_2d_r": 0.021157,
      "decay_3d_r": null,
      "v1_rank": 1,
      "v2_rank": 4,
      "shadow_p_win": 0.75,
      "shadow_expected_r": 0.875,
      "shadow_threshold": 0.52,
      "v2_recommended": true,
      "shadow_model_source": "fallback",
      "shadow_market_regime": "risk_off",
      "regime_status": "risk_off",
      "volatility_bucket": "high"
    },
    {
      "date": "2026-07-14",
      "exit_date": "2026-07-15",
      "ticker": "INCO",
      "mode": "t1",
      "rank": 4,
      "score": 97.5164,
      "predicted_p_win": 0.7252,
      "predicted_p_win_source": "shadow_p_win",
      "passes_live_threshold": true,
      "horizon_days": 1,
      "bars_to_exit": 1,
      "entry": 4930.0,
      "stop": 4384.1219,
      "tp1": 5475.8781,
      "tp2": 6021.7563,
      "exit_price": 4900.0,
      "outcome": "horizon_exit",
      "win": false,
      "tp1_touched": false,
      "tp2_touched": false,
      "realized_r": -0.108953,
      "return_pct": -1.206389,
      "mae_r": -0.164872,
      "mfe_r": 0.109915,
      "atr_pct": 5.5363,
      "avg_vol_20d": 11732225.0,
      "ret_20d_pct": -2.8571,
      "liquidity_bucket": "high",
      "score_bucket": "95-100",
      "decay_1d_r": -0.108953,
      "decay_2d_r": -0.127208,
      "decay_3d_r": null,
      "v1_rank": 4,
      "v2_rank": 5,
      "shadow_p_win": 0.7252,
      "shadow_expected_r": 0.813,
      "shadow_threshold": 0.52,
      "v2_recommended": true,
      "shadow_model_source": "fallback",
      "shadow_market_regime": "risk_off",
      "regime_status": "risk_off",
      "volatility_bucket": "high"
    },
    {
      "date": "2026-07-13",
      "exit_date": "2026-07-14",
      "ticker": "UNTR",
      "mode": "t1",
      "rank": 2,
      "score": 99.3285,
      "predicted_p_win": 0.7919,
      "predicted_p_win_source": "shadow_p_win",
      "passes_live_threshold": true,
      "horizon_days": 1,
      "bars_to_exit": 1,
      "entry": 25900.0,
      "stop": 24335.5985,
      "tp1": 27464.4015,
      "tp2": 29028.8029,
      "exit_price": 27500.0,
      "outcome": "horizon_exit",
      "win": true,
      "tp1_touched": true,
      "tp2_touched": false,
      "realized_r": 0.919841,
      "return_pct": 5.555985,
      "mae_r": -0.191767,
      "mfe_r": 1.118639,
      "atr_pct": 3.0201,
      "avg_vol_20d": 4786865.0,
      "ret_20d_pct": 15.1111,
      "liquidity_bucket": "high",
      "score_bucket": "95-100",
      "decay_1d_r": 0.919841,
      "decay_2d_r": 0.792444,
      "decay_3d_r": 0.617273,
      "v1_rank": 2,
      "v2_rank": 1,
      "shadow_p_win": 0.7919,
      "shadow_expected_r": 0.9798,
      "shadow_threshold": 0.52,
      "v2_recommended": true,
      "shadow_model_source": "fallback",
      "shadow_market_regime": "risk_off",
      "regime_status": "risk_off",
      "volatility_bucket": "mid"
    },
    {
      "date": "2026-07-13",
      "exit_date": "2026-07-14",
      "ticker": "ADRO",
      "mode": "t1",
      "rank": 5,
      "score": 96.8,
      "predicted_p_win": 0.7733,
      "predicted_p_win_source": "shadow_p_win",
      "passes_live_threshold": true,
      "horizon_days": 1,
      "bars_to_exit": 1,
      "entry": 2450.0,
      "stop": 2306.8655,
      "tp1": 2593.1345,
      "tp2": 2736.269,
      "exit_price": 2480.0,
      "outcome": "horizon_exit",
      "win": true,
      "tp1_touched": false,
      "tp2_touched": false,
      "realized_r": 0.106159,
      "return_pct": 0.620204,
      "mae_r": -0.139729,
      "mfe_r": 0.279457,
      "atr_pct": 2.9211,
      "avg_vol_20d": 30727200.0,
      "ret_20d_pct": 7.4561,
      "liquidity_bucket": "high",
      "score_bucket": "95-100",
      "decay_1d_r": 0.106159,
      "decay_2d_r": 0.175779,
      "decay_3d_r": -0.102701,
      "v1_rank": 5,
      "v2_rank": 2,
      "shadow_p_win": 0.7733,
      "shadow_expected_r": 0.9332,
      "shadow_threshold": 0.52,
      "v2_recommended": true,
      "shadow_model_source": "fallback",
      "shadow_market_regime": "risk_off",
      "regime_status": "risk_off",
      "volatility_bucket": "low"
    },
    {
      "date": "2026-07-13",
      "exit_date": "2026-07-14",
      "ticker": "PGAS",
      "mode": "t1",
      "rank": 1,
      "score": 99.409,
      "predicted_p_win": 0.749,
      "predicted_p_win_source": "shadow_p_win",
      "passes_live_threshold": true,
      "horizon_days": 1,
      "bars_to_exit": 1,
      "entry": 1530.0,
      "stop": 1417.5215,
      "tp1": 1642.4785,
      "tp2": 1754.9571,
      "exit_price": 1490.0,
      "outcome": "horizon_exit",
      "win": false,
      "tp1_touched": false,
      "tp2_touched": false,
      "realized_r": -0.435994,
      "return_pct": -3.205229,
      "mae_r": -0.355623,
      "mfe_r": 0.044453,
      "atr_pct": 3.6758,
      "avg_vol_20d": 29552745.0,
      "ret_20d_pct": 0.0,
      "liquidity_bucket": "high",
      "score_bucket": "95-100",
      "decay_1d_r": -0.435994,
      "decay_2d_r": -0.3474,
      "decay_3d_r": -0.480292,
      "v1_rank": 1,
      "v2_rank": 3,
      "shadow_p_win": 0.749,
      "shadow_expected_r": 0.8725,
      "shadow_threshold": 0.52,
      "v2_recommended": true,
      "shadow_model_source": "fallback",
      "shadow_market_regime": "risk_off",
      "regime_status": "risk_off",
      "volatility_bucket": "mid"
    },
    {
      "date": "2026-07-13",
      "exit_date": "2026-07-14",
      "ticker": "BBNI",
      "mode": "t1",
      "rank": 3,
      "score": 98.0086,
      "predicted_p_win": 0.7301,
      "predicted_p_win_source": "shadow_p_win",
      "passes_live_threshold": true,
      "horizon_days": 1,
      "bars_to_exit": 1,
      "entry": 3530.0,
      "stop": 3256.6245,
      "tp1": 3803.3755,
      "tp2": 4076.7509,
      "exit_price": 3470.0,
      "outcome": "horizon_exit",
      "win": false,
      "tp1_touched": false,
      "tp2_touched": false,
      "realized_r": -0.296186,
      "return_pct": -2.293768,
      "mae_r": -0.256058,
      "mfe_r": 0.109739,
      "atr_pct": 3.8722,
      "avg_vol_20d": 59100425.0,
      "ret_20d_pct": -0.8427,
      "liquidity_bucket": "high",
      "score_bucket": "95-100",
      "decay_1d_r": -0.296186,
      "decay_2d_r": -0.150379,
      "decay_3d_r": -0.296186,
      "v1_rank": 3,
      "v2_rank": 4,
      "shadow_p_win": 0.7301,
      "shadow_expected_r": 0.8252,
      "shadow_threshold": 0.52,
      "v2_recommended": true,
      "shadow_model_source": "fallback",
      "shadow_market_regime": "risk_off",
      "regime_status": "risk_off",
      "volatility_bucket": "mid"
    },
    {
      "date": "2026-07-13",
      "exit_date": "2026-07-14",
      "ticker": "MEDC",
      "mode": "t1",
      "rank": 4,
      "score": 97.0582,
      "predicted_p_win": 0.7206,
      "predicted_p_win_source": "shadow_p_win",
      "passes_live_threshold": true,
      "horizon_days": 1,
      "bars_to_exit": 1,
      "entry": 1185.0,
      "stop": 1071.8365,
      "tp1": 1298.1635,
      "tp2": 1411.3269,
      "exit_price": 1250.0,
      "outcome": "horizon_exit",
      "win": true,
      "tp1_touched": false,
      "tp2_touched": false,
      "realized_r": 0.50955,
      "return_pct": 4.866034,
      "mae_r": 0.0,
      "mfe_r": 0.706942,
      "atr_pct": 4.7748,
      "avg_vol_20d": 48761295.0,
      "ret_20d_pct": -3.2653,
      "liquidity_bucket": "high",
      "score_bucket": "95-100",
      "decay_1d_r": 0.50955,
      "decay_2d_r": 0.377463,
      "decay_3d_r": 0.597609,
      "v1_rank": 4,
      "v2_rank": 5,
      "shadow_p_win": 0.7206,
      "shadow_expected_r": 0.8015,
      "shadow_threshold": 0.52,
      "v2_recommended": true,
      "shadow_model_source": "fallback",
      "shadow_market_regime": "risk_off",
      "regime_status": "risk_off",
      "volatility_bucket": "high"
    },
    {
      "date": "2026-07-10",
      "exit_date": "2026-07-13",
      "ticker": "INTP",
      "mode": "t1",
      "rank": 1,
      "score": 98.3499,
      "predicted_p_win": 0.7795,
      "predicted_p_win_source": "shadow_p_win",
      "passes_live_threshold": true,
      "horizon_days": 1,
      "bars_to_exit": 1,
      "entry": 4490.0,
      "stop": 4215.2017,
      "tp1": 4764.7983,
      "tp2": 5039.5967,
      "exit_price": 4490.0,
      "outcome": "horizon_exit",
      "win": false,
      "tp1_touched": false,
      "tp2_touched": false,
      "realized_r": -0.098036,
      "return_pct": -0.6,
      "mae_r": -0.072781,
      "mfe_r": 0.072781,
      "atr_pct": 3.0601,
      "avg_vol_20d": 1946720.0,
      "ret_20d_pct": 7.9327,
      "liquidity_bucket": "mid",
      "score_bucket": "95-100",
      "decay_1d_r": -0.098036,
      "decay_2d_r": 0.119542,
      "decay_3d_r": 0.228331,
      "v1_rank": 1,
      "v2_rank": 1,
      "shadow_p_win": 0.7795,
      "shadow_expected_r": 0.9487,
      "shadow_threshold": 0.52,
      "v2_recommended": true,
      "shadow_model_source": "fallback",
      "shadow_market_regime": "risk_off",
      "regime_status": "risk_off",
      "volatility_bucket": "mid"
    },
    {
      "date": "2026-07-10",
      "exit_date": "2026-07-13",
      "ticker": "ADRO",
      "mode": "t1",
      "rank": 5,
      "score": 93.9344,
      "predicted_p_win": 0.7501,
      "predicted_p_win_source": "shadow_p_win",
      "passes_live_threshold": false,
      "horizon_days": 1,
      "bars_to_exit": 1,
      "entry": 2390.0,
      "stop": 2254.3167,
      "tp1": 2525.6833,
      "tp2": 2661.3666,
      "exit_price": 2450.0,
      "outcome": "horizon_exit",
      "win": true,
      "tp1_touched": false,
      "tp2_touched": false,
      "realized_r": 0.334971,
      "return_pct": 1.901674,
      "mae_r": -0.442206,
      "mfe_r": 0.442206,
      "atr_pct": 2.8386,
      "avg_vol_20d": 30097615.0,
      "ret_20d_pct": 6.2222,
      "liquidity_bucket": "high",
      "score_bucket": "90-95",
      "decay_1d_r": 0.334971,
      "decay_2d_r": 0.5553,
      "decay_3d_r": 0.628744,
      "v1_rank": 5,
      "v2_rank": 2,
      "shadow_p_win": 0.7501,
      "shadow_expected_r": 0.8752,
      "shadow_threshold": 0.52,
      "v2_recommended": true,
      "shadow_model_source": "fallback",
      "shadow_market_regime": "risk_off",
      "regime_status": "risk_off",
      "volatility_bucket": "low"
    },
    {
      "date": "2026-07-10",
      "exit_date": "2026-07-13",
      "ticker": "MEDC",
      "mode": "t1",
      "rank": 2,
      "score": 97.1257,
      "predicted_p_win": 0.7213,
      "predicted_p_win_source": "shadow_p_win",
      "passes_live_threshold": true,
      "horizon_days": 1,
      "bars_to_exit": 1,
      "entry": 1175.0,
      "stop": 1058.5163,
      "tp1": 1291.4837,
      "tp2": 1407.9675,
      "exit_price": 1185.0,
      "outcome": "horizon_exit",
      "win": true,
      "tp1_touched": false,
      "tp2_touched": false,
      "realized_r": 0.025025,
      "return_pct": 0.248085,
      "mae_r": 0.0,
      "mfe_r": 0.300471,
      "atr_pct": 4.9568,
      "avg_vol_20d": 51661110.0,
      "ret_20d_pct": -3.2922,
      "liquidity_bucket": "high",
      "score_bucket": "95-100",
      "decay_1d_r": 0.025025,
      "decay_2d_r": 0.58109,
      "decay_3d_r": 0.452767,
      "v1_rank": 2,
      "v2_rank": 3,
      "shadow_p_win": 0.7213,
      "shadow_expected_r": 0.8032,
      "shadow_threshold": 0.52,
      "v2_recommended": true,
      "shadow_model_source": "fallback",
      "shadow_market_regime": "risk_off",
      "regime_status": "risk_off",
      "volatility_bucket": "high"
    },
    {
      "date": "2026-07-10",
      "exit_date": "2026-07-13",
      "ticker": "BBNI",
      "mode": "t1",
      "rank": 3,
      "score": 95.3819,
      "predicted_p_win": 0.7038,
      "predicted_p_win_source": "shadow_p_win",
      "passes_live_threshold": true,
      "horizon_days": 1,
      "bars_to_exit": 1,
      "entry": 3420.0,
      "stop": 3156.3649,
      "tp1": 3683.6351,
      "tp2": 3947.2702,
      "exit_price": 3530.0,
      "outcome": "horizon_exit",
      "win": true,
      "tp1_touched": false,
      "tp2_touched": false,
      "realized_r": 0.337948,
      "return_pct": 2.605117,
      "mae_r": -0.189656,
      "mfe_r": 0.568968,
      "atr_pct": 3.8543,
      "avg_vol_20d": 60264785.0,
      "ret_20d_pct": -2.2857,
      "liquidity_bucket": "high",
      "score_bucket": "95-100",
      "decay_1d_r": 0.337948,
      "decay_2d_r": 0.111157,
      "decay_3d_r": 0.262351,
      "v1_rank": 3,
      "v2_rank": 4,
      "shadow_p_win": 0.7038,
      "shadow_expected_r": 0.7595,
      "shadow_threshold": 0.52,
      "v2_recommended": true,
      "shadow_model_source": "fallback",
      "shadow_market_regime": "risk_off",
      "regime_status": "risk_off",
      "volatility_bucket": "mid"
    },
    {
      "date": "2026-07-10",
      "exit_date": "2026-07-13",
      "ticker": "AKRA",
      "mode": "t1",
      "rank": 4,
      "score": 95.3253,
      "predicted_p_win": 0.7033,
      "predicted_p_win_source": "shadow_p_win",
      "passes_live_threshold": true,
      "horizon_days": 1,
      "bars_to_exit": 1,
      "entry": 1320.0,
      "stop": 1218.9827,
      "tp1": 1421.0173,
      "tp2": 1522.0346,
      "exit_price": 1325.0,
      "outcome": "horizon_exit",
      "win": false,
      "tp1_touched": false,
      "tp2_touched": false,
      "realized_r": -0.029079,
      "return_pct": -0.222538,
      "mae_r": -0.049496,
      "mfe_r": 0.148489,
      "atr_pct": 3.8264,
      "avg_vol_20d": 15581220.0,
      "ret_20d_pct": 4.3478,
      "liquidity_bucket": "high",
      "score_bucket": "95-100",
      "decay_1d_r": -0.029079,
      "decay_2d_r": 0.118891,
      "decay_3d_r": 0.217537,
      "v1_rank": 4,
      "v2_rank": 5,
      "shadow_p_win": 0.7033,
      "shadow_expected_r": 0.7583,
      "shadow_threshold": 0.52,
      "v2_recommended": true,
      "shadow_model_source": "fallback",
      "shadow_market_regime": "risk_off",
      "regime_status": "risk_off",
      "volatility_bucket": "mid"
    },
    {
      "date": "2026-07-09",
      "exit_date": "2026-07-10",
      "ticker": "MEDC",
      "mode": "t1",
      "rank": 1,
      "score": 100.0,
      "predicted_p_win": 0.75,
      "predicted_p_win_source": "shadow_p_win",
      "passes_live_threshold": true,
      "horizon_days": 1,
      "bars_to_exit": 1,
      "entry": 1165.0,
      "stop": 1044.9406,
      "tp1": 1285.0594,
      "tp2": 1405.1188,
      "exit_price": 1175.0,
      "outcome": "horizon_exit",
      "win": true,
      "tp1_touched": false,
      "tp2_touched": false,
      "realized_r": 0.024779,
      "return_pct": 0.255365,
      "mae_r": -0.083292,
      "mfe_r": 0.20823,
      "atr_pct": 5.1528,
      "avg_vol_20d": 56426570.0,
      "ret_20d_pct": -2.5105,
      "liquidity_bucket": "high",
      "score_bucket": "95-100",
      "decay_1d_r": 0.024779,
      "decay_2d_r": 0.10778,
      "decay_3d_r": 0.647284,
      "v1_rank": 1,
      "v2_rank": 1,
      "shadow_p_win": 0.75,
      "shadow_expected_r": 0.875,
      "shadow_threshold": 0.52,
      "v2_recommended": true,
      "shadow_model_source": "fallback",
      "shadow_market_regime": "risk_off",
      "regime_status": "risk_off",
      "volatility_bucket": "high"
    },
    {
      "date": "2026-07-09",
      "exit_date": "2026-07-10",
      "ticker": "UNTR",
      "mode": "t1",
      "rank": 5,
      "score": 95.6584,
      "predicted_p_win": 0.749,
      "predicted_p_win_source": "shadow_p_win",
      "passes_live_threshold": true,
      "horizon_days": 1,
      "bars_to_exit": 1,
      "entry": 24050.0,
      "stop": 22552.2326,
      "tp1": 25547.7674,
      "tp2": 27045.5347,
      "exit_price": 24500.0,
      "outcome": "horizon_exit",
      "win": true,
      "tp1_touched": false,
      "tp2_touched": false,
      "realized_r": 0.203052,
      "return_pct": 1.264553,
      "mae_r": 0.0,
      "mfe_r": 0.367213,
      "atr_pct": 3.1139,
      "avg_vol_20d": 4836950.0,
      "ret_20d_pct": 9.3182,
      "liquidity_bucket": "high",
      "score_bucket": "95-100",
      "decay_1d_r": 0.203052,
      "decay_2d_r": 1.134505,
      "decay_3d_r": 2.199023,
      "v1_rank": 5,
      "v2_rank": 2,
      "shadow_p_win": 0.749,
      "shadow_expected_r": 0.8725,
      "shadow_threshold": 0.52,
      "v2_recommended": true,
      "shadow_model_source": "fallback",
      "shadow_market_regime": "risk_off",
      "regime_status": "risk_off",
      "volatility_bucket": "mid"
    },
    {
      "date": "2026-07-09",
      "exit_date": "2026-07-10",
      "ticker": "ASII",
      "mode": "t1",
      "rank": 4,
      "score": 96.8313,
      "predicted_p_win": 0.7274,
      "predicted_p_win_source": "shadow_p_win",
      "passes_live_threshold": true,
      "horizon_days": 1,
      "bars_to_exit": 1,
      "entry": 4880.0,
      "stop": 4527.2882,
      "tp1": 5232.7118,
      "tp2": 5585.4237,
      "exit_price": 4810.0,
      "outcome": "horizon_exit",
      "win": false,
      "tp1_touched": false,
      "tp2_touched": false,
      "realized_r": -0.280782,
      "return_pct": -2.029406,
      "mae_r": -0.311869,
      "mfe_r": 0.0,
      "atr_pct": 3.6139,
      "avg_vol_20d": 62500720.0,
      "ret_20d_pct": 3.8298,
      "liquidity_bucket": "high",
      "score_bucket": "95-100",
      "decay_1d_r": -0.280782,
      "decay_2d_r": -0.167772,
      "decay_3d_r": -0.083014,
      "v1_rank": 4,
      "v2_rank": 3,
      "shadow_p_win": 0.7274,
      "shadow_expected_r": 0.8185,
      "shadow_threshold": 0.52,
      "v2_recommended": true,
      "shadow_model_source": "fallback",
      "shadow_market_regime": "risk_off",
      "regime_status": "risk_off",
      "volatility_bucket": "mid"
    },
    {
      "date": "2026-07-09",
      "exit_date": "2026-07-10",
      "ticker": "BBTN",
      "mode": "t1",
      "rank": 2,
      "score": 97.6983,
      "predicted_p_win": 0.727,
      "predicted_p_win_source": "shadow_p_win",
      "passes_live_threshold": true,
      "horizon_days": 1,
      "bars_to_exit": 1,
      "entry": 1170.0,
      "stop": 1067.0722,
      "tp1": 1272.9278,
      "tp2": 1375.8556,
      "exit_price": 1180.0,
      "outcome": "horizon_exit",
      "win": true,
      "tp1_touched": false,
      "tp2_touched": false,
      "realized_r": 0.028612,
      "return_pct": 0.251709,
      "mae_r": 0.0,
      "mfe_r": 0.291466,
      "atr_pct": 4.3986,
      "avg_vol_20d": 21249395.0,
      "ret_20d_pct": -3.3058,
      "liquidity_bucket": "high",
      "score_bucket": "95-100",
      "decay_1d_r": 0.028612,
      "decay_2d_r": 0.270651,
      "decay_3d_r": 0.125428,
      "v1_rank": 2,
      "v2_rank": 4,
      "shadow_p_win": 0.727,
      "shadow_expected_r": 0.8175,
      "shadow_threshold": 0.52,
      "v2_recommended": true,
      "shadow_model_source": "fallback",
      "shadow_market_regime": "risk_off",
      "regime_status": "risk_off",
      "volatility_bucket": "high"
    },
    {
      "date": "2026-07-09",
      "exit_date": "2026-07-10",
      "ticker": "BBCA",
      "mode": "t1",
      "rank": 3,
      "score": 97.2117,
      "predicted_p_win": 0.7221,
      "predicted_p_win_source": "shadow_p_win",
      "passes_live_threshold": true,
      "horizon_days": 1,
      "bars_to_exit": 1,
      "entry": 6200.0,
      "stop": 5727.2823,
      "tp1": 6672.7177,
      "tp2": 7145.4354,
      "exit_price": 6175.0,
      "outcome": "horizon_exit",
      "win": false,
      "tp1_touched": false,
      "tp2_touched": false,
      "realized_r": -0.131394,
      "return_pct": -1.001815,
      "mae_r": -0.158657,
      "mfe_r": 0.211543,
      "atr_pct": 3.8122,
      "avg_vol_20d": 247900855.0,
      "ret_20d_pct": 9.7345,
      "liquidity_bucket": "high",
      "score_bucket": "95-100",
      "decay_1d_r": -0.131394,
      "decay_2d_r": -0.025993,
      "decay_3d_r": -0.236796,
      "v1_rank": 3,
      "v2_rank": 5,
      "shadow_p_win": 0.7221,
      "shadow_expected_r": 0.8052,
      "shadow_threshold": 0.52,
      "v2_recommended": true,
      "shadow_model_source": "fallback",
      "shadow_market_regime": "risk_off",
      "regime_status": "risk_off",
      "volatility_bucket": "mid"
    },
    {
      "date": "2026-07-08",
      "exit_date": "2026-07-09",
      "ticker": "UNTR",
      "mode": "t1",
      "rank": 3,
      "score": 100.0,
      "predicted_p_win": 0.7903,
      "predicted_p_win_source": "shadow_p_win",
      "passes_live_threshold": true,
      "horizon_days": 1,
      "bars_to_exit": 1,
      "entry": 24300.0,
      "stop": 22771.6351,
      "tp1": 25828.3649,
      "tp2": 27356.7297,
      "exit_price": 24050.0,
      "outcome": "horizon_exit",
      "win": false,
      "tp1_touched": false,
      "tp2_touched": false,
      "realized_r": -0.258397,
      "return_pct": -1.625206,
      "mae_r": -0.31079,
      "mfe_r": 0.049072,
      "atr_pct": 3.1448,
      "avg_vol_20d": 5015385.0,
      "ret_20d_pct": 11.0857,
      "liquidity_bucket": "high",
      "score_bucket": "95-100",
      "decay_1d_r": -0.258397,
      "decay_2d_r": 0.035005,
      "decay_3d_r": 0.94781,
      "v1_rank": 3,
      "v2_rank": 1,
      "shadow_p_win": 0.7903,
      "shadow_expected_r": 0.9757,
      "shadow_threshold": 0.52,
      "v2_recommended": true,
      "shadow_model_source": "fallback",
      "shadow_market_regime": "risk_off",
      "regime_status": "risk_off",
      "volatility_bucket": "mid"
    },
    {
      "date": "2026-07-08",
      "exit_date": "2026-07-09",
      "ticker": "BBCA",
      "mode": "t1",
      "rank": 1,
      "score": 100.0,
      "predicted_p_win": 0.75,
      "predicted_p_win_source": "shadow_p_win",
      "passes_live_threshold": true,
      "horizon_days": 1,
      "bars_to_exit": 1,
      "entry": 6175.0,
      "stop": 5688.9963,
      "tp1": 6661.0037,
      "tp2": 7147.0074,
      "exit_price": 6200.0,
      "outcome": "horizon_exit",
      "win": false,
      "tp1_touched": false,
      "tp2_touched": false,
      "realized_r": -0.024974,
      "return_pct": -0.196559,
      "mae_r": -0.2572,
      "mfe_r": 0.05144,
      "atr_pct": 3.9353,
      "avg_vol_20d": 276211365.0,
      "ret_20d_pct": 19.9029,
      "liquidity_bucket": "high",
      "score_bucket": "95-100",
      "decay_1d_r": -0.024974,
      "decay_2d_r": -0.076234,
      "decay_3d_r": 0.026286,
      "v1_rank": 1,
      "v2_rank": 2,
      "shadow_p_win": 0.75,
      "shadow_expected_r": 0.875,
      "shadow_threshold": 0.52,
      "v2_recommended": true,
      "shadow_model_source": "fallback",
      "shadow_market_regime": "risk_off",
      "regime_status": "risk_off",
      "volatility_bucket": "mid"
    },
    {
      "date": "2026-07-08",
      "exit_date": "2026-07-09",
      "ticker": "MEDC",
      "mode": "t1",
      "rank": 2,
      "score": 100.0,
      "predicted_p_win": 0.75,
      "predicted_p_win_source": "shadow_p_win",
      "passes_live_threshold": true,
      "horizon_days": 1,
      "bars_to_exit": 1,
      "entry": 1170.0,
      "stop": 1048.3976,
      "tp1": 1291.6024,
      "tp2": 1413.2049,
      "exit_price": 1165.0,
      "outcome": "horizon_exit",
      "win": false,
      "tp1_touched": false,
      "tp2_touched": false,
      "realized_r": -0.098703,
      "return_pct": -1.025855,
      "mae_r": -0.123353,
      "mfe_r": 0.287823,
      "atr_pct": 5.1967,
      "avg_vol_20d": 55153270.0,
      "ret_20d_pct": -4.0984,
      "liquidity_bucket": "high",
      "score_bucket": "95-100",
      "decay_1d_r": -0.098703,
      "decay_2d_r": -0.016755,
      "decay_3d_r": 0.065192,
      "v1_rank": 2,
      "v2_rank": 3,
      "shadow_p_win": 0.75,
      "shadow_expected_r": 0.875,
      "shadow_threshold": 0.52,
      "v2_recommended": true,
      "shadow_model_source": "fallback",
      "shadow_market_regime": "risk_off",
      "regime_status": "risk_off",
      "volatility_bucket": "high"
    },
    {
      "date": "2026-07-08",
      "exit_date": "2026-07-09",
      "ticker": "BBTN",
      "mode": "t1",
      "rank": 4,
      "score": 99.2986,
      "predicted_p_win": 0.743,
      "predicted_p_win_source": "shadow_p_win",
      "passes_live_threshold": true,
      "horizon_days": 1,
      "bars_to_exit": 1,
      "entry": 1175.0,
      "stop": 1069.5393,
      "tp1": 1280.4607,
      "tp2": 1385.9214,
      "exit_price": 1170.0,
      "outcome": "horizon_exit",
      "win": false,
      "tp1_touched": false,
      "tp2_touched": false,
      "realized_r": -0.114095,
      "return_pct": -1.024043,
      "mae_r": -0.189644,
      "mfe_r": 0.142233,
      "atr_pct": 4.4877,
      "avg_vol_20d": 21568235.0,
      "ret_20d_pct": 0.0,
      "liquidity_bucket": "high",
      "score_bucket": "95-100",
      "decay_1d_r": -0.114095,
      "decay_2d_r": -0.019604,
      "decay_3d_r": 0.216621,
      "v1_rank": 4,
      "v2_rank": 4,
      "shadow_p_win": 0.743,
      "shadow_expected_r": 0.8575,
      "shadow_threshold": 0.52,
      "v2_recommended": true,
      "shadow_model_source": "fallback",
      "shadow_market_regime": "risk_off",
      "regime_status": "risk_off",
      "volatility_bucket": "high"
    },
    {
      "date": "2026-07-08",
      "exit_date": "2026-07-09",
      "ticker": "AKRA",
      "mode": "t1",
      "rank": 5,
      "score": 98.1549,
      "predicted_p_win": 0.7315,
      "predicted_p_win_source": "shadow_p_win",
      "passes_live_threshold": true,
      "horizon_days": 1,
      "bars_to_exit": 1,
      "entry": 1320.0,
      "stop": 1213.258,
      "tp1": 1426.742,
      "tp2": 1533.484,
      "exit_price": 1300.0,
      "outcome": "horizon_exit",
      "win": false,
      "tp1_touched": false,
      "tp2_touched": false,
      "realized_r": -0.26091,
      "return_pct": -2.109848,
      "mae_r": -0.23421,
      "mfe_r": 0.046842,
      "atr_pct": 4.0433,
      "avg_vol_20d": 18575875.0,
      "ret_20d_pct": 7.3171,
      "liquidity_bucket": "high",
      "score_bucket": "95-100",
      "decay_1d_r": -0.26091,
      "decay_2d_r": -0.074198,
      "decay_3d_r": -0.02752,
      "v1_rank": 5,
      "v2_rank": 5,
      "shadow_p_win": 0.7315,
      "shadow_expected_r": 0.8288,
      "shadow_threshold": 0.52,
      "v2_recommended": true,
      "shadow_model_source": "fallback",
      "shadow_market_regime": "risk_off",
      "regime_status": "risk_off",
      "volatility_bucket": "high"
    }
  ]
}